speechpro/__init__.py
speechpro/cli.py
speechpro/cloud/__init__.py
speechpro/cloud/speech/__init__.py
speechpro/cloud/speech/common/__init__.py
speechpro/cloud/speech/common/rest/__init__.py
speechpro/cloud/speech/common/rest/cloud_client/__init__.py
speechpro/cloud/speech/common/rest/cloud_client/cloud_api_client.py
speechpro/cloud/speech/common/rest/cloud_client/configuration.py
speechpro/cloud/speech/common/rest/cloud_client/rest.py
speechpro/cloud/speech/common/rest/cloud_client/api/__init__.py
speechpro/cloud/speech/common/rest/cloud_client/api/session_api.py
speechpro/cloud/speech/common/rest/cloud_client/models/__init__.py
speechpro/cloud/speech/common/rest/cloud_client/models/auth_request_dto.py
speechpro/cloud/speech/common/rest/cloud_client/models/auth_response_dto.py
speechpro/cloud/speech/common/rest/cloud_client/models/auth_status_dto.py
speechpro/cloud/speech/common/rest/cloud_client/models/credentials.py
speechpro/cloud/speech/common/rest/cloud_client/models/exception_model.py
speechpro/cloud/speech/recognition/__init__.py
speechpro/cloud/speech/recognition/enums.py
speechpro/cloud/speech/recognition/rest/__init__.py
speechpro/cloud/speech/recognition/rest/cloud_client/__init__.py
speechpro/cloud/speech/recognition/rest/cloud_client/cloud_api_client.py
speechpro/cloud/speech/recognition/rest/cloud_client/configuration.py
speechpro/cloud/speech/recognition/rest/cloud_client/rest.py
speechpro/cloud/speech/recognition/rest/cloud_client/run.py
speechpro/cloud/speech/recognition/rest/cloud_client/api/__init__.py
speechpro/cloud/speech/recognition/rest/cloud_client/api/packages_api.py
speechpro/cloud/speech/recognition/rest/cloud_client/api/recognize_api.py
speechpro/cloud/speech/recognition/rest/cloud_client/api/session_api.py
speechpro/cloud/speech/recognition/rest/cloud_client/models/__init__.py
speechpro/cloud/speech/recognition/rest/cloud_client/models/advanced_recognition_request_dto.py
speechpro_cloud_python-0.1.10.dist-info/AUTHORS.rst
speechpro_cloud_python-0.1.10.dist-info/LICENSE
speechpro_cloud_python-0.1.10.dist-info/METADATA
speechpro_cloud_python-0.1.10.dist-info/WHEEL
speechpro_cloud_python-0.1.10.dist-info/entry_points.txt
speechpro_cloud_python-0.1.10.dist-info/top_level.txt
speechpro_cloud_python-0.1.10.dist-info/RECORD
