Metadata-Version: 2.1
Name: speechpro-cloud-python
Version: 0.1.10
Summary: Python клиент для API распознавания и синтеза речи Облака ЦРТ
Home-page: https://github.com/speechpro/cloud-python
Author: Dmitry Kozhedubov
Author-email: hiisi13@gmail.com
License: MIT license
Keywords: speechpro
Platform: UNKNOWN
Classifier: Development Status :: 2 - Pre-Alpha
Classifier: Intended Audience :: Developers
Classifier: License :: OSI Approved :: MIT License
Classifier: Natural Language :: English
Classifier: Programming Language :: Python :: 3
Classifier: Programming Language :: Python :: 3.5
Classifier: Programming Language :: Python :: 3.6
Classifier: Programming Language :: Python :: 3.7
Classifier: Programming Language :: Python :: 3.8
Requires-Python: >=3.5
Requires-Dist: Click (>=7.0)
Requires-Dist: certifi (>=14.05.14)
Requires-Dist: six (>=1.10)
Requires-Dist: python-dateutil (>=2.5.3)
Requires-Dist: setuptools (>=21.0.0)
Requires-Dist: urllib3 (>=1.15.1)
Requires-Dist: toml (==0.10.1)
